synctoolbox/__init__.py
synctoolbox/dtw/__init__.py
synctoolbox/dtw/anchor.py
synctoolbox/dtw/core.py
synctoolbox/dtw/cost.py
synctoolbox/dtw/mrmsdtw.py
synctoolbox/dtw/utils.py
synctoolbox/dtw/visualization.py
synctoolbox/feature/__init__.py
synctoolbox/feature/chroma.py
synctoolbox/feature/csv_tools.py
synctoolbox/feature/dlnco.py
synctoolbox/feature/filterbank.py
synctoolbox/feature/novelty.py
synctoolbox/feature/pitch.py
synctoolbox/feature/pitch_onset.py
synctoolbox/feature/utils.py
synctoolbox-1.4.0.dist-info/licenses/LICENCE
synctoolbox-1.4.0.dist-info/WHEEL
synctoolbox-1.4.0.dist-info/METADATA
synctoolbox-1.4.0.dist-info/RECORD
