Metadata-Version: 2.4
Name: synctoolbox
Version: 1.4.0
Summary: Python Package for Efficient, Robust, and Accurate Music Synchronization (Sync Toolbox)
Author: Yigitcan Özer, Michael Krause, Thomas Prätzlich, Jonathan Driedger
Author-email: Meinard Müller <meinard.mueller@audiolabs-erlangen.de>
Requires-Python: >=3.8, <3.13.0
Classifier: License :: OSI Approved :: MIT License
Classifier: Programming Language :: Python
Classifier: Intended Audience :: Developers
Classifier: Topic :: Multimedia :: Sound/Audio :: Analysis
Classifier: Programming Language :: Python :: 3
License-File: LICENCE
Requires-Dist: librosa >= 0.8.0, < 1.0.0
Requires-Dist: matplotlib >= 3.1.0, < 4.0.0
Requires-Dist: music21 >= 5.7.0, < 6.0.0
Requires-Dist: numba >= 0.58.1, < 0.60.0
Requires-Dist: numpy >= 1.17.0, < 2.0.0
Requires-Dist: pandas >= 1.0.0, < 2.0.0
Requires-Dist: pretty_midi >= 0.2.0, < 1.0.0
Requires-Dist: soundfile >= 0.9.0, < 1.0.0
Requires-Dist: scipy >= 1.7.0, < 2.0.0
Requires-Dist: libfmp >= 1.2.0, < 2.0.0
Requires-Dist: flit >= 3.10.0 ; extra == "develop"
Requires-Dist: ipython >= 8.10.0 ; extra == "develop"
Requires-Dist: jupyter ; extra == "develop"
Requires-Dist: nbstripout ; extra == "develop"
Requires-Dist: sphinx == 4.0.* ; extra == "doc"
Requires-Dist: sphinx_rtd_theme == 0.5.* ; extra == "doc"
Requires-Dist: pytest == 6.2.* ; extra == "test"
Project-URL: Documentation, https://meinardmueller.github.io/synctoolbox/build/html/index.html
Project-URL: Download, https://github.com/meinardmueller/synctoolbox
Project-URL: Homepage, https://github.com/meinardmueller/synctoolbox
Project-URL: Repository, https://github.com/meinardmueller/synctoolbox
Provides-Extra: develop
Provides-Extra: doc
Provides-Extra: test
